Metadata-Version: 2.1
Name: MyPackage-vR01
Version: 0.0.2
Summary: This is my Package
Home-page: UNKNOWN
Author: Me
License: UNKNOWN
Platform: UNKNOWN
